textual_dad_joke/__init__.py
textual_dad_joke/__main__.py
textual_dad_joke/dad_joke.py
textual_dad_joke/py.typed
textual_dad_joke-0.0.1.dist-info/METADATA
textual_dad_joke-0.0.1.dist-info/WHEEL
textual_dad_joke-0.0.1.dist-info/top_level.txt
textual_dad_joke-0.0.1.dist-info/RECORD
