Metadata-Version: 2.1
Name: textual-dad-joke
Version: 0.0.1
Summary: A dad joke widget for your Textual applications
Home-page: https://github.com/davep/textual-dad-joke
Author: Dave Pearson
Author-email: davep@davep.org
Maintainer: Dave Pearson
Maintainer-email: davep@davep.org
License: License :: OSI Approved :: MIT License
Project-URL: Documentation, https://github.com/davep/textual-dad-joke/blob/main/README.md
Project-URL: Source, https://github.com/davep/textual-dad-joke
Project-URL: Issues, https://github.com/davep/textual-dad-joke/issues
Project-URL: Discussions, https://github.com/davep/textual-dad-joke/discussions
Keywords: terminal,library,file system,filesystem,dialog
Classifier: License :: OSI Approved :: MIT License
Classifier: Environment :: Console
Classifier: Development Status :: 3 - Alpha
Classifier: Intended Audience :: Developers
Classifier: Operating System :: OS Independent
Classifier: Programming Language :: Python :: 3.8
Classifier: Programming Language :: Python :: 3.9
Classifier: Programming Language :: Python :: 3.10
Classifier: Programming Language :: Python :: 3.11
Classifier: Topic :: Terminals
Classifier: Topic :: Software Development :: Libraries
Classifier: Typing :: Typed
Requires-Python: >=3.8
Requires-Dist: textual >=0.47.0
